protoc_gen_pyhttp/__init__.py
protoc_gen_pyhttp/http.py
protoc_gen_pyhttp/main.py
protoc_gen_pyhttp/template.py
protoc_gen_pyhttp/util.py
protoc_gen_pyhttp-1.0.0rc3.dist-info/LICENSE
protoc_gen_pyhttp-1.0.0rc3.dist-info/METADATA
protoc_gen_pyhttp-1.0.0rc3.dist-info/WHEEL
protoc_gen_pyhttp-1.0.0rc3.dist-info/entry_points.txt
protoc_gen_pyhttp-1.0.0rc3.dist-info/top_level.txt
protoc_gen_pyhttp-1.0.0rc3.dist-info/RECORD
