Metadata-Version: 2.1
Name: protoc-gen-pyhttp
Version: 1.0.0rc3
Summary: Generate server classes that correspond to services defined in http-protobuf
Author-email: azicen <chenjiazi@aliyun.com>
Project-URL: Homepage, https://github.com/azicen/protoc-gen-pyhttp
Project-URL: Bug Tracker, https://github.com/azicen/protoc-gen-pyhttp/issues
Classifier: Programming Language :: Python :: 3
Classifier: License :: OSI Approved :: MIT License
Classifier: Operating System :: OS Independent
Requires-Python: >=3.10
License-File: LICENSE
